README
setup.py
cortanaanalytics/__init__.py
cortanaanalytics/anomalydetection.py
cortanaanalytics/recommendations.py
cortanaanalytics/textanalytics.py
cortanaanalytics.egg-info/PKG-INFO
cortanaanalytics.egg-info/SOURCES.txt
cortanaanalytics.egg-info/dependency_links.txt
cortanaanalytics.egg-info/not-zip-safe
cortanaanalytics.egg-info/requires.txt
cortanaanalytics.egg-info/top_level.txt