Metadata-Version: 1.1
Name: cortanaanalytics
Version: 0.0.4
Summary: Python wrappers of Cortana Analytics services
Home-page: https://github.com/crwilcox/cortanaanalytics
Author: Microsoft Corporation
Author-email: ptvshelp@microsoft.com
License: MIT
Platform: UNKNOWN
Classifier: Development Status :: 3 - Alpha
Classifier: License :: OSI Approved :: MIT License
Classifier: Programming Language :: Python
Classifier: Programming Language :: Python :: 3.5
Classifier: Programming Language :: Python :: 3.4
Classifier: Programming Language :: Python :: 3 :: Only
